contributors_txt/__init__.py
contributors_txt/__main__.py
contributors_txt/const.py
contributors_txt/create_content.py
contributors_txt/extract_comment.py
contributors_txt/normalize.py
contributors_txt/update_content.py
contributors_txt-1.0.0.dist-info/LICENSE
contributors_txt-1.0.0.dist-info/METADATA
contributors_txt-1.0.0.dist-info/WHEEL
contributors_txt-1.0.0.dist-info/entry_points.txt
contributors_txt-1.0.0.dist-info/top_level.txt
contributors_txt-1.0.0.dist-info/RECORD
